itis_dakota/__init__.py
itis_dakota/_version.py
itis_dakota-1.5.11.data/platlib/dakota/environment/__init__.py
itis_dakota-1.5.11.data/platlib/dakota/environment/environment.cpython-310-aarch64-linux-gnu.so
itis_dakota.libs/libaec-34bb4966.so.0.0.8
itis_dakota.libs/libblas-8ed0a6f9.so.3.8.0
itis_dakota.libs/libboost_atomic-4e495271.so.1.78.0
itis_dakota.libs/libboost_filesystem-ca604eb0.so.1.78.0
itis_dakota.libs/libboost_program_options-4a9a4d98.so.1.78.0
itis_dakota.libs/libboost_regex-bdb71c82.so.1.78.0
itis_dakota.libs/libboost_serialization-b1f38196.so.1.78.0
itis_dakota.libs/libboost_system-f6e25492.so.1.78.0
itis_dakota.libs/libgfortran-8a9a71bc.so.5.0.0
itis_dakota.libs/libgsl-f7298b36.so.23.1.0
itis_dakota.libs/libgslcblas-cf1da87e.so.0.0.0
itis_dakota.libs/libhdf5-463e48d5.so.103.1.0
itis_dakota.libs/libhdf5_cpp-2cd3d47c.so.103.1.0
itis_dakota.libs/libhdf5_hl-74316838.so.100.1.2
itis_dakota.libs/libhdf5_hl_cpp-c8056f99.so.100.1.3
itis_dakota.libs/libicudata-d4bb2d37.so.60.3
itis_dakota.libs/libicui18n-b245c686.so.60.3
itis_dakota.libs/libicuuc-9464c5e7.so.60.3
itis_dakota.libs/liblapack-8d137073.so.3.8.0
itis_dakota.libs/libsz-81b556a2.so.2.0.1
itis_dakota-1.5.11.dist-info/LICENSE.txt
itis_dakota-1.5.11.dist-info/METADATA
itis_dakota-1.5.11.dist-info/WHEEL
itis_dakota-1.5.11.dist-info/entry_points.txt
itis_dakota-1.5.11.dist-info/RECORD
