Metadata-Version: 2.1
Name: itis-dakota
Version: 1.5.11
Summary: Dakota wheel built by the IT'IS Foundation, Zurich, Switzerland
Home-page: https://github.com/ITISFoundation/itis-dakota
Author: Werner Van Geit
License: Copyright (C) IT'IS Foundation - All Rights Reserved
Project-URL: Homepage, https://github.com/ITISFoundation/itis-dakota
Project-URL: Repository, https://github.com/ITISFoundation/itis-dakota.git
Project-URL: Issues, https://github.com/ITISFoundation/itis-dakota/issues
Requires-Python: >=3.8
Requires-Dist: numpy
